Metadata-Version: 2.1
Name: sit_django_mail
Version: 0.0.2
Summary: Sample Django App
Home-page: https://google.com/
Author: jasirmj
Author-email: jasirmj@gmail.com
Maintainer: jasirmj
Maintainer-email: jasirmj@gmail.com
License: MIT
Keywords: django
Classifier: Environment :: Web Environment
Classifier: Framework :: Django
Classifier: Intended Audience :: Developers
Classifier: License :: OSI Approved :: MIT License
Classifier: Operating System :: OS Independent
Classifier: Programming Language :: Python :: 3
Classifier: Programming Language :: Python :: 3.7
Classifier: Programming Language :: Python :: 3.8
Classifier: Topic :: Software Development :: Libraries :: Python Modules
License-File: LICENSE
